{
    "type": "powah:energizing",
    "ingredients": [{
        "item": "allthecompressed:diamond_block_3x"
    }],
"energy": 196830000,
    "result": {
        "item": "allthecompressed:niotic_crystal_block_3x"
    },
    "conditions": [{
        "type": "forge:and",
        "values": [{
                "type": "forge:not",
                "value": {
                    "type": "forge:mod_loaded",
                    "modid": "compressium"
                }
            },
            {
                "type": "forge:mod_loaded",
                "modid": "powah"
            }
        ]
    }]
}
